crockford32.cpython-310-x86_64-linux-gnu.so
crockford32-1.0.2.dist-info/LICENSE
crockford32-1.0.2.dist-info/RECORD
crockford32-1.0.2.dist-info/WHEEL
crockford32-1.0.2.dist-info/top_level.txt
crockford32-1.0.2.dist-info/METADATA
