Metadata-Version: 2.1
Name: crockford32
Version: 1.0.2
Summary: An implementation of Crockford's Base32 encoding for resource identifiers
Home-page: https://github.com/pat-jpnk/crockford32
Author: Patrick Japink
Author-email: jpnk.pat@gmail.com
License: MIT
Requires-Python: >=3.7
License-File: LICENSE
Provides-Extra: test
Requires-Dist: pytest ; extra == 'test'
